{ 
  "status": "solved",
  "git-revision": 0.93,
  "git-date": "Mon_Dec_19_16:41:15_2022_-0500",
  "annotations": [
{ "type"  : "star",   "pixelx": 1363.33,         "pixely": 982.45,         "name"  : "Miaplacidus",     "names" : [ "Miaplacidus", "β Car" ] } ,
{ "type"  : "star",   "pixelx": 340.99,         "pixely": 624.85,         "name"  : "Rigil Kentaurus / Toliman / Bungula",     "names" : [ "Rigil Kentaurus / Toliman / Bungula", "α1 Cen" ] } ,
{ "type"  : "star",   "pixelx": 403.204,         "pixely": 656.57,         "name"  : "Proxima / Proxima Centauri",     "names" : [ "Proxima / Proxima Centauri", "α Cen C" ] } ,
{ "type"  : "star",   "pixelx": 456.751,         "pixely": 552.345,         "name"  : "Hadar / Agena",     "names" : [ "Hadar / Agena", "β Cen" ] } ,
{ "type"  : "star",   "pixelx": 727.191,         "pixely": 116.15,         "name"  : "Muhlifain",     "names" : [ "Muhlifain", "γ Cen" ] } ,
{ "type"  : "star",   "pixelx": 323.019,         "pixely": 154.215,         "name"  : "Alnair / Baten Kentaurus",     "names" : [ "Alnair / Baten Kentaurus", "ζ Cen" ] } ,
{ "type"  : "star",   "pixelx": 827.422,         "pixely": 561.165,         "name"  : "Acrux",     "names" : [ "Acrux", "α1 Cru / α2 Cru" ] } ,
{ "type"  : "star",   "pixelx": 738.228,         "pixely": 460.539,         "name"  : "Mimosa / Becrux",     "names" : [ "Mimosa / Becrux", "β Cru" ] } ,
{ "type"  : "star",   "pixelx": 799.544,         "pixely": 374.922,         "name"  : "Gacrux",     "names" : [ "Gacrux", "γ Cru" ] } ,
{ "type"  : "star",   "pixelx": 844.641,         "pixely": 476.944,         "name"  : "Ginan",     "names" : [ "Ginan", "ε Cru" ] } ,
{ "type"  : "star",   "pixelx": 668.809,         "pixely": 1024.2,         "name"  : "θ Aps",     "names" : [ "θ Aps" ] } ,
{ "type"  : "star",   "pixelx": 461.436,         "pixely": 1030.47,         "name"  : "κ1 Aps",     "names" : [ "κ1 Aps" ] } ,
{ "type"  : "star",   "pixelx": 1193.33,         "pixely": 669.714,         "name"  : "θ Car",     "names" : [ "θ Car" ] } ,
{ "type"  : "star",   "pixelx": 1372.75,         "pixely": 788.899,         "name"  : "υ Car",     "names" : [ "υ Car" ] } ,
{ "type"  : "star",   "pixelx": 1201.3,         "pixely": 876.92,         "name"  : "ω Car",     "names" : [ "ω Car" ] } ,
{ "type"  : "star",   "pixelx": 1523.84,         "pixely": 783.164,         "name"  : "k Car",     "names" : [ "k Car" ] } ,
{ "type"  : "star",   "pixelx": 1433.27,         "pixely": 723.102,         "name"  : "l Car",     "names" : [ "l Car" ] } ,
{ "type"  : "star",   "pixelx": 1481.35,         "pixely": 705.213,         "name"  : "m Car",     "names" : [ "m Car" ] } ,
{ "type"  : "star",   "pixelx": 1270.46,         "pixely": 604.998,         "name"  : "p Car",     "names" : [ "p Car" ] } ,
{ "type"  : "star",   "pixelx": 1334.49,         "pixely": 621.086,         "name"  : "q Car",     "names" : [ "q Car" ] } ,
{ "type"  : "star",   "pixelx": 1314.55,         "pixely": 472.736,         "name"  : "r Car",     "names" : [ "r Car" ] } ,
{ "type"  : "star",   "pixelx": 1331.28,         "pixely": 522.902,         "name"  : "s Car",     "names" : [ "s Car" ] } ,
{ "type"  : "star",   "pixelx": 1282.96,         "pixely": 533.478,         "name"  : "t1 Car",     "names" : [ "t1 Car" ] } ,
{ "type"  : "star",   "pixelx": 1218.61,         "pixely": 485.532,         "name"  : "u Car",     "names" : [ "u Car" ] } ,
{ "type"  : "star",   "pixelx": 1239.72,         "pixely": 552.88,         "name"  : "w Car",     "names" : [ "w Car" ] } ,
{ "type"  : "star",   "pixelx": 1152.2,         "pixely": 470.606,         "name"  : "x Car",     "names" : [ "x Car" ] } ,
{ "type"  : "star",   "pixelx": 1128.48,         "pixely": 580.354,         "name"  : "z Car",     "names" : [ "z Car" ] } ,
{ "type"  : "star",   "pixelx": 341.122,         "pixely": 624.889,         "name"  : "α2 Cen",     "names" : [ "α2 Cen" ] } ,
{ "type"  : "star",   "pixelx": 906.346,         "pixely": 165.98,         "name"  : "δ Cen",     "names" : [ "δ Cen" ] } ,
{ "type"  : "star",   "pixelx": 471.628,         "pixely": 316.935,         "name"  : "ε Cen",     "names" : [ "ε Cen" ] } ,
{ "type"  : "star",   "pixelx": 25.4506,         "pixely": 90.3478,         "name"  : "η Cen",     "names" : [ "η Cen" ] } ,
{ "type"  : "star",   "pixelx": 1014.04,         "pixely": 573.486,         "name"  : "λ Cen",     "names" : [ "λ Cen" ] } ,
{ "type"  : "star",   "pixelx": 613.76,         "pixely": 151.519,         "name"  : "ξ1 Cen",     "names" : [ "ξ1 Cen" ] } ,
{ "type"  : "star",   "pixelx": 598.982,         "pixely": 166.958,         "name"  : "ξ2 Cen",     "names" : [ "ξ2 Cen" ] } ,
{ "type"  : "star",   "pixelx": 1050.05,         "pixely": 464.007,         "name"  : "ο1 Cen",     "names" : [ "ο1 Cen" ] } ,
{ "type"  : "star",   "pixelx": 1049.42,         "pixely": 466.299,         "name"  : "ο2 Cen",     "names" : [ "ο2 Cen" ] } ,
{ "type"  : "star",   "pixelx": 1132.71,         "pixely": 314.078,         "name"  : "π Cen",     "names" : [ "π Cen" ] } ,
{ "type"  : "star",   "pixelx": 887.983,         "pixely": 220.386,         "name"  : "ρ Cen",     "names" : [ "ρ Cen" ] } ,
{ "type"  : "star",   "pixelx": 802.187,         "pixely": 152.267,         "name"  : "σ Cen",     "names" : [ "σ Cen" ] } ,
{ "type"  : "star",   "pixelx": 746.46,         "pixely": 100.104,         "name"  : "τ Cen",     "names" : [ "τ Cen" ] } ,
{ "type"  : "star",   "pixelx": 272.669,         "pixely": 82.6147,         "name"  : "υ1 Cen",     "names" : [ "υ1 Cen" ] } ,
{ "type"  : "star",   "pixelx": 267.499,         "pixely": 114.102,         "name"  : "υ2 Cen",     "names" : [ "υ2 Cen" ] } ,
{ "type"  : "star",   "pixelx": 665.181,         "pixely": 123.502,         "name"  : "e Cen",     "names" : [ "e Cen" ] } ,
{ "type"  : "star",   "pixelx": 592.509,         "pixely": 119.671,         "name"  : "f Cen",     "names" : [ "f Cen" ] } ,
{ "type"  : "star",   "pixelx": 959.86,         "pixely": 589.829,         "name"  : "j Cen",     "names" : [ "j Cen" ] } ,
{ "type"  : "star",   "pixelx": 636.921,         "pixely": 629.382,         "name"  : "m Cen",     "names" : [ "m Cen" ] } ,
{ "type"  : "star",   "pixelx": 339.101,         "pixely": 467.638,         "name"  : "v Cen",     "names" : [ "v Cen" ] } ,
{ "type"  : "star",   "pixelx": 720.893,         "pixely": 111.915,         "name"  : "w Cen",     "names" : [ "w Cen" ] } ,
{ "type"  : "star",   "pixelx": 1066.42,         "pixely": 295.55,         "name"  : "A Cen",     "names" : [ "A Cen" ] } ,
{ "type"  : "star",   "pixelx": 1103.97,         "pixely": 61.9514,         "name"  : "C1 Cen",     "names" : [ "C1 Cen" ] } ,
{ "type"  : "star",   "pixelx": 1098.2,         "pixely": 70.9686,         "name"  : "C2 Cen",     "names" : [ "C2 Cen" ] } ,
{ "type"  : "star",   "pixelx": 1087.94,         "pixely": 73.6974,         "name"  : "C3 Cen",     "names" : [ "C3 Cen" ] } ,
{ "type"  : "star",   "pixelx": 909.07,         "pixely": 97.5206,         "name"  : "E Cen",     "names" : [ "E Cen" ] } ,
{ "type"  : "star",   "pixelx": 852.082,         "pixely": 310.574,         "name"  : "F Cen",     "names" : [ "F Cen" ] } ,
{ "type"  : "star",   "pixelx": 811.918,         "pixely": 192.052,         "name"  : "G Cen",     "names" : [ "G Cen" ] } ,
{ "type"  : "star",   "pixelx": 656.584,         "pixely": 199.77,         "name"  : "H Cen",     "names" : [ "H Cen" ] } ,
{ "type"  : "star",   "pixelx": 612.47,         "pixely": 522.58,         "name"  : "J Cen",     "names" : [ "J Cen" ] } ,
{ "type"  : "star",   "pixelx": 497.323,         "pixely": 232.526,         "name"  : "K Cen",     "names" : [ "K Cen" ] } ,
{ "type"  : "star",   "pixelx": 417.992,         "pixely": 265.58,         "name"  : "M Cen",     "names" : [ "M Cen" ] } ,
{ "type"  : "star",   "pixelx": 475.054,         "pixely": 352.267,         "name"  : "Q Cen",     "names" : [ "Q Cen" ] } ,
{ "type"  : "star",   "pixelx": 891.978,         "pixely": 1041.04,         "name"  : "ε Cha",     "names" : [ "ε Cha" ] } ,
{ "type"  : "star",   "pixelx": 886.099,         "pixely": 984.742,         "name"  : "κ Cha",     "names" : [ "κ Cha" ] } ,
{ "type"  : "star",   "pixelx": 942.015,         "pixely": 974.002,         "name"  : "π Cha",     "names" : [ "π Cha" ] } ,
{ "type"  : "star",   "pixelx": 402.968,         "pixely": 739.225,         "name"  : "α Cir",     "names" : [ "α Cir" ] } ,
{ "type"  : "star",   "pixelx": 177.59,         "pixely": 656.792,         "name"  : "β Cir",     "names" : [ "β Cir" ] } ,
{ "type"  : "star",   "pixelx": 170.015,         "pixely": 684.226,         "name"  : "γ Cir",     "names" : [ "γ Cir" ] } ,
{ "type"  : "star",   "pixelx": 225.112,         "pixely": 707.632,         "name"  : "δ Cir",     "names" : [ "δ Cir" ] } ,
{ "type"  : "star",   "pixelx": 278.962,         "pixely": 773.122,         "name"  : "ε Cir",     "names" : [ "ε Cir" ] } ,
{ "type"  : "star",   "pixelx": 387.816,         "pixely": 786.717,         "name"  : "ζ Cir",     "names" : [ "ζ Cir" ] } ,
{ "type"  : "star",   "pixelx": 323.015,         "pixely": 756.4,         "name"  : "η Cir",     "names" : [ "η Cir" ] } ,
{ "type"  : "star",   "pixelx": 322.197,         "pixely": 708.767,         "name"  : "θ Cir",     "names" : [ "θ Cir" ] } ,
{ "type"  : "star",   "pixelx": 869.592,         "pixely": 425.166,         "name"  : "δ Cru",     "names" : [ "δ Cru" ] } ,
{ "type"  : "star",   "pixelx": 857.222,         "pixely": 589.239,         "name"  : "ζ Cru",     "names" : [ "ζ Cru" ] } ,
{ "type"  : "star",   "pixelx": 897.251,         "pixely": 609.843,         "name"  : "η Cru",     "names" : [ "η Cru" ] } ,
{ "type"  : "star",   "pixelx": 912.854,         "pixely": 570.218,         "name"  : "θ1 Cru",     "names" : [ "θ1 Cru" ] } ,
{ "type"  : "star",   "pixelx": 908.375,         "pixely": 565.292,         "name"  : "θ2 Cru",     "names" : [ "θ2 Cru" ] } ,
{ "type"  : "star",   "pixelx": 751.326,         "pixely": 499.605,         "name"  : "ι Cru",     "names" : [ "ι Cru" ] } ,
{ "type"  : "star",   "pixelx": 717.32,         "pixely": 484.453,         "name"  : "κ Cru",     "names" : [ "κ Cru" ] } ,
{ "type"  : "star",   "pixelx": 708.14,         "pixely": 447.1,         "name"  : "λ Cru",     "names" : [ "λ Cru" ] } ,
{ "type"  : "star",   "pixelx": 698.809,         "pixely": 386.284,         "name"  : "μ1 Cru",     "names" : [ "μ1 Cru" ] } ,
{ "type"  : "star",   "pixelx": 698.674,         "pixely": 386.009,         "name"  : "μ2 Cru",     "names" : [ "μ2 Cru" ] } ,
{ "type"  : "star",   "pixelx": 801.939,         "pixely": 447.476,         "name"  : "35 Cru",     "names" : [ "35 Cru" ] } ,
{ "type"  : "star",   "pixelx": 761.244,         "pixely": 458.289,         "name"  : "39 Cru",     "names" : [ "39 Cru" ] } ,
{ "type"  : "star",   "pixelx": 92.2431,         "pixely": 263.338,         "name"  : "α Lup",     "names" : [ "α Lup" ] } ,
{ "type"  : "star",   "pixelx": 52.7431,         "pixely": 475.787,         "name"  : "ζ Lup",     "names" : [ "ζ Lup" ] } ,
{ "type"  : "star",   "pixelx": 181.605,         "pixely": 167.385,         "name"  : "ι Lup",     "names" : [ "ι Lup" ] } ,
{ "type"  : "star",   "pixelx": 149.112,         "pixely": 310.822,         "name"  : "ρ Lup",     "names" : [ "ρ Lup" ] } ,
{ "type"  : "star",   "pixelx": 191.469,         "pixely": 327.213,         "name"  : "σ Lup",     "names" : [ "σ Lup" ] } ,
{ "type"  : "star",   "pixelx": 132.452,         "pixely": 158.569,         "name"  : "τ1 Lup",     "names" : [ "τ1 Lup" ] } ,
{ "type"  : "star",   "pixelx": 134.974,         "pixely": 163.436,         "name"  : "τ2 Lup",     "names" : [ "τ2 Lup" ] } ,
{ "type"  : "star",   "pixelx": 163.062,         "pixely": 415.42,         "name"  : "b Lup",     "names" : [ "b Lup" ] } ,
{ "type"  : "star",   "pixelx": 132.742,         "pixely": 450.36,         "name"  : "c Lup",     "names" : [ "c Lup" ] } ,
{ "type"  : "star",   "pixelx": 805.087,         "pixely": 749.109,         "name"  : "α Mus",     "names" : [ "α Mus" ] } ,
{ "type"  : "star",   "pixelx": 775.578,         "pixely": 718.926,         "name"  : "β Mus",     "names" : [ "β Mus" ] } ,
{ "type"  : "star",   "pixelx": 824.49,         "pixely": 842.338,         "name"  : "γ Mus",     "names" : [ "γ Mus" ] } ,
{ "type"  : "star",   "pixelx": 748.585,         "pixely": 829.752,         "name"  : "δ Mus",     "names" : [ "δ Mus" ] } ,
{ "type"  : "star",   "pixelx": 860.807,         "pixely": 712.345,         "name"  : "ε Mus",     "names" : [ "ε Mus" ] } ,
{ "type"  : "star",   "pixelx": 847.119,         "pixely": 722.803,         "name"  : "ζ1 Mus",     "names" : [ "ζ1 Mus" ] } ,
{ "type"  : "star",   "pixelx": 846.797,         "pixely": 698.381,         "name"  : "ζ2 Mus",     "names" : [ "ζ2 Mus" ] } ,
{ "type"  : "star",   "pixelx": 689.971,         "pixely": 724.114,         "name"  : "η Mus",     "names" : [ "η Mus" ] } ,
{ "type"  : "star",   "pixelx": 694.04,         "pixely": 641.929,         "name"  : "θ Mus",     "names" : [ "θ Mus" ] } ,
{ "type"  : "star",   "pixelx": 721.4,         "pixely": 942.303,         "name"  : "ι1 Mus",     "names" : [ "ι1 Mus" ] } ,
{ "type"  : "star",   "pixelx": 715.253,         "pixely": 937.305,         "name"  : "ι2 Mus",     "names" : [ "ι2 Mus" ] } ,
{ "type"  : "star",   "pixelx": 962.732,         "pixely": 683.286,         "name"  : "λ Mus",     "names" : [ "λ Mus" ] } ,
{ "type"  : "star",   "pixelx": 953.958,         "pixely": 684.715,         "name"  : "μ Mus",     "names" : [ "μ Mus" ] } ,
{ "type"  : "star",   "pixelx": 8.92173,         "pixely": 766.035,         "name"  : "ι1 Nor",     "names" : [ "ι1 Nor" ] } ,
{ "type"  : "star",   "pixelx": 177.01,         "pixely": 859.79,         "name"  : "β TrA",     "names" : [ "β TrA" ] } ,
{ "type"  : "star",   "pixelx": 382.588,         "pixely": 897.219,         "name"  : "γ TrA",     "names" : [ "γ TrA" ] } ,
{ "type"  : "star",   "pixelx": 135.553,         "pixely": 920.78,         "name"  : "δ TrA",     "names" : [ "δ TrA" ] } ,
{ "type"  : "star",   "pixelx": 290.212,         "pixely": 878.193,         "name"  : "ε TrA",     "names" : [ "ε TrA" ] } ,
{ "type"  : "star",   "pixelx": 143.607,         "pixely": 1012.25,         "name"  : "θ TrA",     "names" : [ "θ TrA" ] } ,
{ "type"  : "star",   "pixelx": 118.392,         "pixely": 964.128,         "name"  : "ι TrA",     "names" : [ "ι TrA" ] } ,
{ "type"  : "star",   "pixelx": 304.657,         "pixely": 969.459,         "name"  : "κ TrA",     "names" : [ "κ TrA" ] } ,
{ "type"  : "star",   "pixelx": 1369.95,         "pixely": 187.982,         "name"  : "μ Vel",     "names" : [ "μ Vel" ] } ,
{ "type"  : "star",   "pixelx": 1443.76,         "pixely": 163.199,         "name"  : "p Vel",     "names" : [ "p Vel" ] } ,
{ "type"  : "star",   "pixelx": 1490.41,         "pixely": 128.537,         "name"  : "t Vel",     "names" : [ "t Vel" ] } ,
{ "type"  : "star",   "pixelx": 1324.67,         "pixely": 404.828,         "name"  : "x Vel",     "names" : [ "x Vel" ] } ,
{ "type"  : "star",   "pixelx": 1406.3,         "pixely": 453.14,         "name"  : "J Vel",     "names" : [ "J Vel" ] } ,
{ "type"  : "star",   "pixelx": 1478.53,         "pixely": 931.762,         "name"  : "α Vol",     "names" : [ "α Vol" ] } ,
{ "type"   : "ngc",   "names"  : [ "IC 2602", "tet Car Cluster" ],   "pixelx" : 1193.34,   "pixely" : 669.707,   "radius" : 12.3926 },
{ "type"   : "ngc",   "names"  : [ "NGC 3372", "eta Car Nebula", "Carina Nebula" ],   "pixelx" : 1241.97,   "pixely" : 528.96,   "radius" : 30.9814 }
]
}
